safer_yaml/__init__.py
safer_yaml/safer_yaml.py
safer_yaml-0.1.1.dist-info/licenses/LICENSE
safer_yaml-0.1.1.dist-info/METADATA
safer_yaml-0.1.1.dist-info/WHEEL
safer_yaml-0.1.1.dist-info/top_level.txt
safer_yaml-0.1.1.dist-info/RECORD
