Metadata-Version: 2.4
Name: safer-yaml
Version: 0.1.1
Summary: Yaml 1.2 support for Python with a nicer api
Author-email: Chris Bates <1314008+chrsbats@users.noreply.github.com>
License-Expression: MIT
Project-URL: Homepage, https://github.com/chrsbats/safer-yaml
Project-URL: Bug Tracker, https://github.com/chrsbats/safer-yaml/issues
Classifier: Programming Language :: Python :: 3
Classifier: Programming Language :: Python :: 3 :: Only
Classifier: Programming Language :: Python :: 3.9
Classifier: Programming Language :: Python :: 3.10
Classifier: Programming Language :: Python :: 3.11
Classifier: Programming Language :: Python :: 3.12
Classifier: Programming Language :: Python :: 3.13
Classifier: Intended Audience :: Developers
Classifier: Topic :: Utilities
Classifier: Topic :: Text Processing :: Markup
Classifier: Topic :: Software Development :: Libraries :: Python Modules
Classifier: Operating System :: OS Independent
Requires-Python: >=3.9
License-File: LICENSE
Requires-Dist: PyYAML>=6.0.2
Requires-Dist: yamlcore>=0.0.4
Provides-Extra: dev
Requires-Dist: pytest>=8.0.0; extra == "dev"
Requires-Dist: pytest-cov>=5.0.0; extra == "dev"
Requires-Dist: pytest-benchmark>=4.0.0; extra == "dev"
Requires-Dist: flake8>=7.0.0; extra == "dev"
Dynamic: license-file
